{
  "_class": "artboard",
  "backgroundColor": {
    "_class": "color",
    "alpha": 1,
    "blue": 0.9411764705882353,
    "green": 0.9254901960784314,
    "red": 0.9019607843137255
  },
  "booleanOperation": 0,
  "clippingMaskMode": 0,
  "do_objectID": "79056522-03E4-425C-A04D-C3BBEACD3DF7",
  "exportOptions": {
    "_class": "exportOptions",
    "exportFormats": [
      {
        "_class": "exportFormat",
        "absoluteSize": 0,
        "fileFormat": "png",
        "name": "2",
        "namingScheme": 0,
        "scale": 4,
        "visibleScaleType": 0
      }
    ],
    "includedLayerIds": [
    ],
    "layerOptions": 0,
    "shouldTrim": false
  },
  "frame": {
    "_class": "rect",
    "constrainProportions": false,
    "height": 1024,
    "width": 1440,
    "x": 827,
    "y": 888
  },
  "grid": {
    "_class": "simpleGrid",
    "gridSize": 8,
    "isEnabled": false,
    "thickGridTimes": 10
  },
  "groupLayout": {
    "_class": "MSImmutableFreeformGroupLayout"
  },
  "hasBackgroundColor": true,
  "hasClickThrough": true,
  "hasClippingMask": false,
  "horizontalRulerData": {
    "_class": "rulerData",
    "base": 0,
    "guides": [
    ]
  },
  "includeBackgroundColorInExport": true,
  "includeInCloudUpload": true,
  "isFixedToViewport": false,
  "isFlippedHorizontal": false,
  "isFlippedVertical": false,
  "isFlowHome": false,
  "isLocked": false,
  "isVisible": true,
  "layerListExpandedType": 2,
  "layers": [
    {
      "class": "symbolInstance",
      "id": "ADEB4B7C-23D5-401A-9C71-B463CF09386A"
    },
    {
      "class": "group",
      "id": "CEB39A9F-A04C-41D7-BFFB-B1F237B4C1A4"
    },
    {
      "class": "group",
      "id": "9B44956C-C9D1-41E3-B2D6-06EF98E58685"
    },
    {
      "class": "symbolInstance",
      "id": "1945162A-2733-410F-AD9E-230A7357AB3D"
    },
    {
      "class": "symbolInstance",
      "id": "A5411FE4-937C-4B31-96BC-C2D5A35A2424"
    },
    {
      "class": "symbolInstance",
      "id": "E166F78A-18CC-4B78-8D01-FE80E42F0BDE"
    },
    {
      "class": "symbolInstance",
      "id": "4C5A3E9A-032C-4451-9387-B34126BFA8A5"
    },
    {
      "class": "rectangle",
      "id": "8378E65F-946B-41D9-98E4-161B7D6CFB89"
    },
    {
      "class": "shapePath",
      "id": "6D9034F4-F28D-4845-B85B-C98EFC594DEB"
    },
    {
      "class": "rectangle",
      "id": "749CA123-B596-431C-8B72-2E7F26FD23F5"
    },
    {
      "class": "symbolInstance",
      "id": "514EFAC4-6670-459F-B724-F3A9F6E2D80D"
    },
    {
      "class": "symbolInstance",
      "id": "EC4E7F84-0D08-4477-BAE6-AC603AC300A0"
    },
    {
      "class": "group",
      "id": "E33CA1FC-2446-4E3E-856A-A19C7C3A9C9C"
    },
    {
      "class": "group",
      "id": "8086D26F-B227-4335-A191-1CCEDD746975"
    },
    {
      "class": "group",
      "id": "57CED17B-7C0F-4666-8B3A-5C969C7A6FA9"
    },
    {
      "class": "symbolInstance",
      "id": "14533547-3ECD-4436-8A74-DA67513E6027"
    },
    {
      "class": "symbolInstance",
      "id": "BD066B80-A8AA-4C4D-98E2-48737947E78C"
    },
    {
      "class": "shapePath",
      "id": "29CDF017-583E-4A5B-9C6B-FD00B8265CC1"
    },
    {
      "class": "symbolInstance",
      "id": "02A11215-218E-4744-8AAF-9146AB31B8D9"
    },
    {
      "class": "symbolInstance",
      "id": "FB7E82E6-8CC2-418E-8BBA-C309C4C625DD"
    },
    {
      "class": "symbolInstance",
      "id": "C8AD2A05-6ADA-49AB-8F5F-5FAB5B29F80E"
    },
    {
      "class": "symbolInstance",
      "id": "CB921DA7-39AA-4F6F-A0A9-90D88A4E5EA2"
    },
    {
      "class": "symbolInstance",
      "id": "141393D1-D8A0-49A6-89CB-EDFFE40C29EA"
    },
    {
      "class": "symbolInstance",
      "id": "B6F249B7-D213-4CB3-B327-B46CA1E9F2E3"
    },
    {
      "class": "symbolInstance",
      "id": "85E30CCF-DA6F-4E14-AAF7-E83CDEE296EE"
    },
    {
      "class": "group",
      "id": "198EE15F-1EDD-48C2-B5D8-01DCD4BC0A0E"
    },
    {
      "class": "group",
      "id": "5B15FEDD-97DD-441E-8B8A-15D509F99B4D"
    },
    {
      "class": "text",
      "id": "CDA4F934-77EA-4545-A59E-99FED500C4AE"
    },
    {
      "class": "group",
      "id": "5CB8DEC5-4D76-467C-83C9-B61F99F5BBA8"
    }
  ],
  "layout": {
    "_class": "layoutGrid",
    "columnWidth": 76,
    "drawHorizontal": false,
    "drawHorizontalLines": true,
    "drawVertical": true,
    "gutterHeight": 24,
    "gutterWidth": 24,
    "guttersOutside": true,
    "horizontalOffset": 120,
    "isEnabled": true,
    "numberOfColumns": 12,
    "rowHeightMultiplication": 1024,
    "totalWidth": 1200
  },
  "name": "D-Add-group2",
  "nameIsFixed": false,
  "presetDictionary": {
    "allowResizedMatching": 0,
    "height": 1024,
    "name": "Desktop HD",
    "offersLandscapeVariant": 0,
    "width": 1440
  },
  "resizesContent": false,
  "resizingConstraint": 63,
  "resizingType": 0,
  "rotation": 0,
  "shouldBreakMaskChain": true,
  "verticalRulerData": {
    "_class": "rulerData",
    "base": 0,
    "guides": [
    ]
  }
}