{
  "_class": "shapeGroup",
  "booleanOperation": 0,
  "clippingMaskMode": 0,
  "do_objectID": "7477D7E8-0026-41BC-9A05-609B0D5F0E22",
  "frame": {
    "_class": "rect",
    "constrainProportions": true,
    "height": 16,
    "width": 16,
    "x": 4,
    "y": 4
  },
  "groupLayout": {
    "_class": "MSImmutableFreeformGroupLayout"
  },
  "hasClickThrough": false,
  "hasClippingMask": true,
  "isFixedToViewport": false,
  "isFlippedHorizontal": false,
  "isFlippedVertical": false,
  "isLocked": false,
  "isVisible": true,
  "layerListExpandedType": 0,
  "layers": [
    {
      "class": "shapePath",
      "id": "E8C11DE4-564F-4B5A-A94B-9250DF412C71"
    },
    {
      "class": "shapePath",
      "id": "9213F42E-4F05-44AF-83A1-05B3C698FD3B"
    },
    {
      "class": "shapePath",
      "id": "8A8126B9-FD68-4AEA-8807-011EF001CA42"
    },
    {
      "class": "shapePath",
      "id": "6E25F530-C3DD-41A2-BCE0-D4E6D512ED89"
    },
    {
      "class": "shapePath",
      "id": "9CB599A9-AC6C-4BF4-A48C-F10D90137BA0"
    },
    {
      "class": "shapePath",
      "id": "2CB257EC-93A9-4463-A1BD-3E5D4FCB0D16"
    },
    {
      "class": "shapePath",
      "id": "9C1E2977-E162-46B7-A8E1-152DE5A582EA"
    },
    {
      "class": "shapePath",
      "id": "DA534B62-B64F-45DD-9533-ADF26B340EFF"
    }
  ],
  "name": "icon/image/grain_24px",
  "nameIsFixed": false,
  "resizingConstraint": 63,
  "resizingType": 0,
  "rotation": 0,
  "shouldBreakMaskChain": false,
  "style": {
    "_class": "style",
    "blur": {
      "_class": "blur",
      "center": "{0.5, 0.5}",
      "isEnabled": false,
      "motionAngle": 0,
      "radius": 10,
      "saturation": 1,
      "type": 0
    },
    "borderOptions": {
      "_class": "borderOptions",
      "dashPattern": [
      ],
      "isEnabled": true,
      "lineCapStyle": 0,
      "lineJoinStyle": 0
    },
    "borders": [
    ],
    "colorControls": {
      "_class": "colorControls",
      "brightness": 0,
      "contrast": 1,
      "hue": 0,
      "isEnabled": false,
      "saturation": 1
    },
    "contextSettings": {
      "_class": "graphicsContextSettings",
      "blendMode": 0,
      "opacity": 1
    },
    "do_objectID": "5ACFC761-781E-4318-AC0F-B00358845A7D",
    "endMarkerType": 0,
    "fills": [
      {
        "_class": "fill",
        "color": {
          "_class": "color",
          "alpha": 1,
          "blue": 0,
          "green": 0,
          "red": 0
        },
        "contextSettings": {
          "_class": "graphicsContextSettings",
          "blendMode": 0,
          "opacity": 1
        },
        "fillType": 0,
        "gradient": {
          "_class": "gradient",
          "elipseLength": 0,
          "from": "{0.5, 0}",
          "gradientType": 0,
          "stops": [
            {
              "_class": "gradientStop",
              "color": {
                "_class": "color",
                "alpha": 1,
                "blue": 1,
                "green": 1,
                "red": 1
              },
              "position": 0
            },
            {
              "_class": "gradientStop",
              "color": {
                "_class": "color",
                "alpha": 1,
                "blue": 0,
                "green": 0,
                "red": 0
              },
              "position": 1
            }
          ],
          "to": "{0.5, 1}"
        },
        "isEnabled": false,
        "noiseIndex": 0,
        "noiseIntensity": 0,
        "patternFillType": 1,
        "patternTileScale": 1
      }
    ],
    "innerShadows": [
    ],
    "miterLimit": 10,
    "shadows": [
    ],
    "startMarkerType": 0,
    "windingRule": 0
  },
  "windingRule": 0
}