{
  "_class": "shapePath",
  "booleanOperation": -1,
  "clippingMaskMode": 0,
  "do_objectID": "A91486E0-F239-42FA-AC2E-8D81CA58A85A",
  "edited": true,
  "frame": {
    "_class": "rect",
    "constrainProportions": false,
    "height": 2.590000000000032,
    "width": 2.059999999999974,
    "x": 0,
    "y": 0
  },
  "hasClippingMask": false,
  "isClosed": true,
  "isFixedToViewport": false,
  "isFlippedHorizontal": false,
  "isFlippedVertical": false,
  "isLocked": false,
  "isVisible": true,
  "layerListExpandedType": 0,
  "name": "Path",
  "nameIsFixed": false,
  "pointRadiusBehaviour": 1,
  "points": [
    {
      "_class": "curvePoint",
      "cornerRadius": 0,
      "curveFrom": "{0.57766990291260001, 1}",
      "curveMode": 1,
      "curveTo": "{0.57766990291260001, 1}",
      "hasCurveFrom": false,
      "hasCurveTo": false,
      "point": "{0.57766990291260001, 1}"
    },
    {
      "_class": "curvePoint",
      "cornerRadius": 0,
      "curveFrom": "{0.61165048543686895, 1}",
      "curveMode": 4,
      "curveTo": "{0.57766990291260001, 1}",
      "hasCurveFrom": true,
      "hasCurveTo": false,
      "point": "{0.57766990291260001, 1}"
    },
    {
      "_class": "curvePoint",
      "cornerRadius": 0,
      "curveFrom": "{0.62621359223298623, 0.95366795366795243}",
      "curveMode": 4,
      "curveTo": "{0.61650485436891722, 1}",
      "hasCurveFrom": false,
      "hasCurveTo": true,
      "point": "{0.62621359223298623, 0.95366795366795243}"
    },
    {
      "_class": "curvePoint",
      "cornerRadius": 0,
      "curveFrom": "{0.67961165048542072, 0.95366795366795243}",
      "curveMode": 4,
      "curveTo": "{0.62621359223298623, 0.95366795366795243}",
      "hasCurveFrom": true,
      "hasCurveTo": false,
      "point": "{0.62621359223298623, 0.95366795366795243}"
    },
    {
      "_class": "curvePoint",
      "cornerRadius": 0,
      "curveFrom": "{0.71844660194172416, 0.92664092664092845}",
      "curveMode": 4,
      "curveTo": "{0.67961165048542072, 0.95366795366795243}",
      "hasCurveFrom": false,
      "hasCurveTo": true,
      "point": "{0.71844660194172416, 0.92664092664092845}"
    },
    {
      "_class": "curvePoint",
      "cornerRadius": 0,
      "curveFrom": "{0.71844660194172416, 0.90347490347490467}",
      "curveMode": 1,
      "curveTo": "{0.71844660194172416, 0.90347490347490467}",
      "hasCurveFrom": false,
      "hasCurveTo": false,
      "point": "{0.71844660194172416, 0.90347490347490467}"
    },
    {
      "_class": "curvePoint",
      "cornerRadius": 0,
      "curveFrom": "{0.71844660194172416, 0.90347490347490467}",
      "curveMode": 1,
      "curveTo": "{0.71844660194172416, 0.90347490347490467}",
      "hasCurveFrom": false,
      "hasCurveTo": false,
      "point": "{0.71844660194172416, 0.90347490347490467}"
    },
    {
      "_class": "curvePoint",
      "cornerRadius": 0,
      "curveFrom": "{0.74158835710491899, 0.90034299102960424}",
      "curveMode": 4,
      "curveTo": "{0.71844660194172416, 0.90347490347490467}",
      "hasCurveFrom": true,
      "hasCurveTo": false,
      "point": "{0.71844660194172416, 0.90347490347490467}"
    },
    {
      "_class": "curvePoint",
      "cornerRadius": 0,
      "curveFrom": "{0.77883591361178572, 0.85337276274088436}",
      "curveMode": 2,
      "curveTo": "{0.76105957482582609, 0.88793405290733451}",
      "hasCurveFrom": true,
      "hasCurveTo": true,
      "point": "{0.76994774421880596, 0.87065340782410938}"
    },
    {
      "_class": "curvePoint",
      "cornerRadius": 0,
      "curveFrom": "{0.76213592233008964, 0.81853281853282123}",
      "curveMode": 4,
      "curveTo": "{0.77588247067698479, 0.8336673485119509}",
      "hasCurveFrom": false,
      "hasCurveTo": true,
      "point": "{0.76213592233008964, 0.81853281853282123}"
    },
    {
      "_class": "curvePoint",
      "cornerRadius": 0,
      "curveFrom": "{0.79126213592232408, 0.81853281853282123}",
      "curveMode": 4,
      "curveTo": "{0.76213592233008964, 0.81853281853282123}",
      "hasCurveFrom": true,
      "hasCurveTo": false,
      "point": "{0.76213592233008964, 0.81853281853282123}"
    },
    {
      "_class": "curvePoint",
      "cornerRadius": 0,
      "curveFrom": "{0.84951456310679307, 0.81853281853282123}",
      "curveMode": 4,
      "curveTo": "{0.79126213592232408, 0.81853281853282123}",
      "hasCurveFrom": false,
      "hasCurveTo": true,
      "point": "{0.84951456310679307, 0.81853281853282123}"
    },
    {
      "_class": "curvePoint",
      "cornerRadius": 0,
      "curveFrom": "{0.95631067961164828, 0.81853281853282123}",
      "curveMode": 1,
      "curveTo": "{0.95631067961164828, 0.81853281853282123}",
      "hasCurveFrom": false,
      "hasCurveTo": false,
      "point": "{0.95631067961164828, 0.81853281853282123}"
    },
    {
      "_class": "curvePoint",
      "cornerRadius": 0,
      "curveFrom": "{1, 0.81853281853282123}",
      "curveMode": 1,
      "curveTo": "{1, 0.81853281853282123}",
      "hasCurveFrom": false,
      "hasCurveTo": false,
      "point": "{1, 0.81853281853282123}"
    },
    {
      "_class": "curvePoint",
      "cornerRadius": 0,
      "curveFrom": "{1, 0.81853281853282123}",
      "curveMode": 1,
      "curveTo": "{1, 0.81853281853282123}",
      "hasCurveFrom": false,
      "hasCurveTo": false,
      "point": "{1, 0.81853281853282123}"
    },
    {
      "_class": "curvePoint",
      "cornerRadius": 0,
      "curveFrom": "{1, 0.79536679536679744}",
      "curveMode": 1,
      "curveTo": "{1, 0.79536679536679744}",
      "hasCurveFrom": false,
      "hasCurveTo": false,
      "point": "{1, 0.79536679536679744}"
    },
    {
      "_class": "curvePoint",
      "cornerRadius": 0,
      "curveFrom": "{1, 0.76833976833977335}",
      "curveMode": 1,
      "curveTo": "{1, 0.76833976833977335}",
      "hasCurveFrom": false,
      "hasCurveTo": false,
      "point": "{1, 0.76833976833977335}"
    },
    {
      "_class": "curvePoint",
      "cornerRadius": 0,
      "curveFrom": "{0.97087378640776556, 0.72972972972973749}",
      "curveMode": 1,
      "curveTo": "{0.97087378640776556, 0.72972972972973749}",
      "hasCurveFrom": false,
      "hasCurveTo": false,
      "point": "{0.97087378640776556, 0.72972972972973749}"
    },
    {
      "_class": "curvePoint",
      "cornerRadius": 0,
      "curveFrom": "{0.97087378640776556, 0.7027027027027134}",
      "curveMode": 1,
      "curveTo": "{0.97087378640776556, 0.7027027027027134}",
      "hasCurveFrom": false,
      "hasCurveTo": false,
      "point": "{0.97087378640776556, 0.7027027027027134}"
    },
    {
      "_class": "curvePoint",
      "cornerRadius": 0,
      "curveFrom": "{0.96013597397071293, 0.63133465557926349}",
      "curveMode": 4,
      "curveTo": "{0.97087378640776556, 0.67181467181467802}",
      "hasCurveFrom": true,
      "hasCurveTo": false,
      "point": "{0.97087378640776556, 0.67181467181467802}"
    },
    {
      "_class": "curvePoint",
      "cornerRadius": 0,
      "curveFrom": "{0.90776699029126207, 0.5598455598455705}",
      "curveMode": 4,
      "curveTo": "{0.93861733922552237, 0.59315457718076203}",
      "hasCurveFrom": false,
      "hasCurveTo": true,
      "point": "{0.90776699029126207, 0.5598455598455705}"
    },
    {
      "_class": "curvePoint",
      "cornerRadius": 0,
      "curveFrom": "{0.90776699029126207, 0.53667953667954671}",
      "curveMode": 1,
      "curveTo": "{0.90776699029126207, 0.53667953667954671}",
      "hasCurveFrom": false,
      "hasCurveTo": false,
      "point": "{0.90776699029126207, 0.53667953667954671}"
    },
    {
      "_class": "curvePoint",
      "cornerRadius": 0,
      "curveFrom": "{0.90776699029126207, 0.53667953667954671}",
      "curveMode": 1,
      "curveTo": "{0.90776699029126207, 0.53667953667954671}",
      "hasCurveFrom": false,
      "hasCurveTo": false,
      "point": "{0.90776699029126207, 0.53667953667954671}"
    },
    {
      "_class": "curvePoint",
      "cornerRadius": 0,
      "curveFrom": "{0.90776699029126207, 0.50579150579151144}",
      "curveMode": 1,
      "curveTo": "{0.90776699029126207, 0.50579150579151144}",
      "hasCurveFrom": false,
      "hasCurveTo": false,
      "point": "{0.90776699029126207, 0.50579150579151144}"
    },
    {
      "_class": "curvePoint",
      "cornerRadius": 0,
      "curveFrom": "{0.78155339805825519, 0.3474903474903564}",
      "curveMode": 4,
      "curveTo": "{0.87378640776699312, 0.46718146718147546}",
      "hasCurveFrom": true,
      "hasCurveTo": false,
      "point": "{0.87378640776699312, 0.46718146718147546}"
    },
    {
      "_class": "curvePoint",
      "cornerRadius": 0,
      "curveFrom": "{0.74271844660193798, 0.32432432432433261}",
      "curveMode": 4,
      "curveTo": "{0.78155339805825519, 0.3474903474903564}",
      "hasCurveFrom": false,
      "hasCurveTo": true,
      "point": "{0.74271844660193798, 0.32432432432433261}"
    },
    {
      "_class": "curvePoint",
      "cornerRadius": 0,
      "curveFrom": "{0.74271844660193798, 0.32432432432433261}",
      "curveMode": 1,
      "curveTo": "{0.74271844660193798, 0.32432432432433261}",
      "hasCurveFrom": false,
      "hasCurveTo": false,
      "point": "{0.74271844660193798, 0.32432432432433261}"
    },
    {
      "_class": "curvePoint",
      "cornerRadius": 0,
      "curveFrom": "{0.78155339805825519, 0.32432432432433261}",
      "curveMode": 4,
      "curveTo": "{0.78155339805825519, 0.32432432432433261}",
      "hasCurveFrom": true,
      "hasCurveTo": false,
      "point": "{0.78155339805825519, 0.32432432432433261}"
    },
    {
      "_class": "curvePoint",
      "cornerRadius": 0,
      "curveFrom": "{0.81067961165048963, 0.2586872586872726}",
      "curveMode": 4,
      "curveTo": "{0.78155339805825519, 0.28957528957529699}",
      "hasCurveFrom": false,
      "hasCurveTo": true,
      "point": "{0.81067961165048963, 0.2586872586872726}"
    },
    {
      "_class": "curvePoint",
      "cornerRadius": 0,
      "curveFrom": "{0.83980582524272418, 0.2586872586872726}",
      "curveMode": 1,
      "curveTo": "{0.83980582524272418, 0.2586872586872726}",
      "hasCurveFrom": false,
      "hasCurveTo": false,
      "point": "{0.83980582524272418, 0.2586872586872726}"
    },
    {
      "_class": "curvePoint",
      "cornerRadius": 0,
      "curveFrom": "{0.84189045075400726, 0.22529197688205105}",
      "curveMode": 4,
      "curveTo": "{0.83980582524272418, 0.23552123552124887}",
      "hasCurveFrom": true,
      "hasCurveTo": false,
      "point": "{0.83980582524272418, 0.23552123552124887}"
    },
    {
      "_class": "curvePoint",
      "cornerRadius": 0,
      "curveFrom": "{0.83980582524272418, 0.1737451737451782}",
      "curveMode": 4,
      "curveTo": "{0.84189045075400726, 0.21486246327241135}",
      "hasCurveFrom": true,
      "hasCurveTo": true,
      "point": "{0.83980582524272418, 0.20463320463321352}"
    },
    {
      "_class": "curvePoint",
      "cornerRadius": 0,
      "curveFrom": "{0.74271844660195174, 0.12741312741314165}",
      "curveMode": 4,
      "curveTo": "{0.80097087378640686, 0.1660231660231776}",
      "hasCurveFrom": false,
      "hasCurveTo": true,
      "point": "{0.74271844660195174, 0.12741312741314165}"
    },
    {
      "_class": "curvePoint",
      "cornerRadius": 0,
      "curveFrom": "{0.74271844660195174, 0.12741312741314165}",
      "curveMode": 1,
      "curveTo": "{0.74271844660195174, 0.12741312741314165}",
      "hasCurveFrom": false,
      "hasCurveTo": false,
      "point": "{0.74271844660195174, 0.12741312741314165}"
    },
    {
      "_class": "curvePoint",
      "cornerRadius": 0,
      "curveFrom": "{0.74271844660195174, 0.12741312741314165}",
      "curveMode": 1,
      "curveTo": "{0.74271844660195174, 0.12741312741314165}",
      "hasCurveFrom": false,
      "hasCurveTo": false,
      "point": "{0.74271844660195174, 0.12741312741314165}"
    },
    {
      "_class": "curvePoint",
      "cornerRadius": 0,
      "curveFrom": "{0.74271844660195174, 0.12741312741314165}",
      "curveMode": 1,
      "curveTo": "{0.74271844660195174, 0.12741312741314165}",
      "hasCurveFrom": false,
      "hasCurveTo": false,
      "point": "{0.74271844660195174, 0.12741312741314165}"
    },
    {
      "_class": "curvePoint",
      "cornerRadius": 0,
      "curveFrom": "{0.71844660194175169, 0.10810810810811819}",
      "curveMode": 1,
      "curveTo": "{0.71844660194175169, 0.10810810810811819}",
      "hasCurveFrom": false,
      "hasCurveTo": false,
      "point": "{0.71844660194175169, 0.10810810810811819}"
    },
    {
      "_class": "curvePoint",
      "cornerRadius": 0,
      "curveFrom": "{0.64723658720508337, 0.054947187930032081}",
      "curveMode": 4,
      "curveTo": "{0.67961165048543448, 0.081081081081094131}",
      "hasCurveFrom": true,
      "hasCurveTo": false,
      "point": "{0.67961165048543448, 0.081081081081094131}"
    },
    {
      "_class": "curvePoint",
      "cornerRadius": 0,
      "curveFrom": "{0.57281553398057927, 0.011583011583011879}",
      "curveMode": 4,
      "curveTo": "{0.61143345260987936, 0.031648131580602944}",
      "hasCurveFrom": false,
      "hasCurveTo": true,
      "point": "{0.57281553398057927, 0.011583011583011879}"
    },
    {
      "_class": "curvePoint",
      "cornerRadius": 0,
      "curveFrom": "{0.54854368932037934, 0.011583011583011879}",
      "curveMode": 1,
      "curveTo": "{0.54854368932037934, 0.011583011583011879}",
      "hasCurveFrom": false,
      "hasCurveTo": false,
      "point": "{0.54854368932037934, 0.011583011583011879}"
    },
    {
      "_class": "curvePoint",
      "cornerRadius": 0,
      "curveFrom": "{0.51456310679611039, 0.011583011583011879}",
      "curveMode": 1,
      "curveTo": "{0.51456310679611039, 0.011583011583011879}",
      "hasCurveFrom": false,
      "hasCurveTo": false,
      "point": "{0.51456310679611039, 0.011583011583011879}"
    },
    {
      "_class": "curvePoint",
      "cornerRadius": 0,
      "curveFrom": "{0.51456310679611039, 0.011583011583011879}",
      "curveMode": 1,
      "curveTo": "{0.51456310679611039, 0.011583011583011879}",
      "hasCurveFrom": false,
      "hasCurveTo": false,
      "point": "{0.51456310679611039, 0.011583011583011879}"
    },
    {
      "_class": "curvePoint",
      "cornerRadius": 0,
      "curveFrom": "{0.47087378640775862, 0.011583011583011879}",
      "curveMode": 1,
      "curveTo": "{0.47087378640775862, 0.011583011583011879}",
      "hasCurveFrom": false,
      "hasCurveTo": false,
      "point": "{0.47087378640775862, 0.011583011583011879}"
    },
    {
      "_class": "curvePoint",
      "cornerRadius": 0,
      "curveFrom": "{0.47087378640775862, 0.030888030888035337}",
      "curveMode": 1,
      "curveTo": "{0.47087378640775862, 0.030888030888035337}",
      "hasCurveFrom": false,
      "hasCurveTo": false,
      "point": "{0.47087378640775862, 0.030888030888035337}"
    },
    {
      "_class": "curvePoint",
      "cornerRadius": 0,
      "curveFrom": "{0.47087378640775862, 0.057915057915059395}",
      "curveMode": 1,
      "curveTo": "{0.47087378640775862, 0.057915057915059395}",
      "hasCurveFrom": false,
      "hasCurveTo": false,
      "point": "{0.47087378640775862, 0.057915057915059395}"
    },
    {
      "_class": "curvePoint",
      "cornerRadius": 0,
      "curveFrom": "{0.45005976383452362, 0.054480772549743407}",
      "curveMode": 4,
      "curveTo": "{0.47087378640775862, 0.057915057915059395}",
      "hasCurveFrom": true,
      "hasCurveTo": false,
      "point": "{0.47087378640775862, 0.057915057915059395}"
    },
    {
      "_class": "curvePoint",
      "cornerRadius": 0,
      "curveFrom": "{0.40776699029125518, 0.057915057915059395}",
      "curveMode": 4,
      "curveTo": "{0.42858101286447636, 0.054480772549743407}",
      "hasCurveFrom": true,
      "hasCurveTo": true,
      "point": "{0.40776699029125518, 0.057915057915059395}"
    },
    {
      "_class": "curvePoint",
      "cornerRadius": 0,
      "curveFrom": "{0.30130680109834712, 0.0057977954834690787}",
      "curveMode": 4,
      "curveTo": "{0.35436893203882069, 0}",
      "hasCurveFrom": true,
      "hasCurveTo": true,
      "point": "{0.32524271844660002, 0}"
    },
    {
      "_class": "curvePoint",
      "cornerRadius": 0,
      "curveFrom": "{0.26699029126214485, 0.034749034749046614}",
      "curveMode": 4,
      "curveTo": "{0.28069023097892642, 0.018096096963980859}",
      "hasCurveFrom": false,
      "hasCurveTo": true,
      "point": "{0.26699029126214485, 0.034749034749046614}"
    },
    {
      "_class": "curvePoint",
      "cornerRadius": 0,
      "curveFrom": "{0.23300970873787585, 0.034749034749046614}",
      "curveMode": 1,
      "curveTo": "{0.23300970873787585, 0.034749034749046614}",
      "hasCurveFrom": false,
      "hasCurveTo": false,
      "point": "{0.23300970873787585, 0.034749034749046614}"
    },
    {
      "_class": "curvePoint",
      "cornerRadius": 0,
      "curveFrom": "{0.23300970873787585, 0.034749034749046614}",
      "curveMode": 1,
      "curveTo": "{0.23300970873787585, 0.034749034749046614}",
      "hasCurveFrom": false,
      "hasCurveTo": false,
      "point": "{0.23300970873787585, 0.034749034749046614}"
    },
    {
      "_class": "curvePoint",
      "cornerRadius": 0,
      "curveFrom": "{0.18446601941748966, 0.034749034749046614}",
      "curveMode": 1,
      "curveTo": "{0.18446601941748966, 0.034749034749046614}",
      "hasCurveFrom": false,
      "hasCurveTo": false,
      "point": "{0.18446601941748966, 0.034749034749046614}"
    },
    {
      "_class": "curvePoint",
      "cornerRadius": 0,
      "curveFrom": "{0.17831710452570396, 0.080952021454812423}",
      "curveMode": 4,
      "curveTo": "{0.18446601941748966, 0.034749034749046614}",
      "hasCurveFrom": true,
      "hasCurveTo": false,
      "point": "{0.18446601941748966, 0.034749034749046614}"
    },
    {
      "_class": "curvePoint",
      "cornerRadius": 0,
      "curveFrom": "{0.18446601941747587, 0.1737451737451782}",
      "curveMode": 4,
      "curveTo": "{0.17831710452570396, 0.1275421870394014}",
      "hasCurveFrom": false,
      "hasCurveTo": true,
      "point": "{0.18446601941747587, 0.1737451737451782}"
    },
    {
      "_class": "curvePoint",
      "cornerRadius": 0,
      "curveFrom": "{0.18446601941747587, 0.19691119691120196}",
      "curveMode": 1,
      "curveTo": "{0.18446601941747587, 0.19691119691120196}",
      "hasCurveFrom": false,
      "hasCurveTo": false,
      "point": "{0.18446601941747587, 0.19691119691120196}"
    },
    {
      "_class": "curvePoint",
      "cornerRadius": 0,
      "curveFrom": "{0.18446601941747587, 0.19691119691120196}",
      "curveMode": 1,
      "curveTo": "{0.18446601941747587, 0.19691119691120196}",
      "hasCurveFrom": false,
      "hasCurveTo": false,
      "point": "{0.18446601941747587, 0.19691119691120196}"
    },
    {
      "_class": "curvePoint",
      "cornerRadius": 0,
      "curveFrom": "{0.18446601941747587, 0.19691119691120196}",
      "curveMode": 1,
      "curveTo": "{0.18446601941747587, 0.19691119691120196}",
      "hasCurveFrom": false,
      "hasCurveTo": false,
      "point": "{0.18446601941747587, 0.19691119691120196}"
    },
    {
      "_class": "curvePoint",
      "cornerRadius": 0,
      "curveFrom": "{0.24271844660194483, 0.22007722007722572}",
      "curveMode": 1,
      "curveTo": "{0.24271844660194483, 0.22007722007722572}",
      "hasCurveFrom": false,
      "hasCurveTo": false,
      "point": "{0.24271844660194483, 0.22007722007722572}"
    },
    {
      "_class": "curvePoint",
      "cornerRadius": 0,
      "curveFrom": "{0.24271844660194483, 0.22007722007722572}",
      "curveMode": 1,
      "curveTo": "{0.24271844660194483, 0.22007722007722572}",
      "hasCurveFrom": false,
      "hasCurveTo": false,
      "point": "{0.24271844660194483, 0.22007722007722572}"
    },
    {
      "_class": "curvePoint",
      "cornerRadius": 0,
      "curveFrom": "{0.24271844660194483, 0.22007722007722572}",
      "curveMode": 1,
      "curveTo": "{0.24271844660194483, 0.22007722007722572}",
      "hasCurveFrom": false,
      "hasCurveTo": false,
      "point": "{0.24271844660194483, 0.22007722007722572}"
    },
    {
      "_class": "curvePoint",
      "cornerRadius": 0,
      "curveFrom": "{0.24271844660194483, 0.22007722007722572}",
      "curveMode": 1,
      "curveTo": "{0.24271844660194483, 0.22007722007722572}",
      "hasCurveFrom": false,
      "hasCurveTo": false,
      "point": "{0.24271844660194483, 0.22007722007722572}"
    },
    {
      "_class": "curvePoint",
      "cornerRadius": 0,
      "curveFrom": "{0.22752839115344503, 0.2657871968507351}",
      "curveMode": 4,
      "curveTo": "{0.24271844660194483, 0.24710424710424977}",
      "hasCurveFrom": true,
      "hasCurveTo": false,
      "point": "{0.24271844660194483, 0.24710424710424977}"
    },
    {
      "_class": "curvePoint",
      "cornerRadius": 0,
      "curveFrom": "{0.21359223300971034, 0.30888030888032042}",
      "curveMode": 4,
      "curveTo": "{0.21759297134037939, 0.28686000489697933}",
      "hasCurveFrom": false,
      "hasCurveTo": true,
      "point": "{0.21359223300971034, 0.30888030888032042}"
    },
    {
      "_class": "curvePoint",
      "cornerRadius": 0,
      "curveFrom": "{0.1747572815533931, 0.30888030888032042}",
      "curveMode": 1,
      "curveTo": "{0.1747572815533931, 0.30888030888032042}",
      "hasCurveFrom": false,
      "hasCurveTo": false,
      "point": "{0.1747572815533931, 0.30888030888032042}"
    },
    {
      "_class": "curvePoint",
      "cornerRadius": 0,
      "curveFrom": "{0.1262135922330069, 0.2779922779922851}",
      "curveMode": 1,
      "curveTo": "{0.1262135922330069, 0.2779922779922851}",
      "hasCurveFrom": false,
      "hasCurveTo": false,
      "point": "{0.1262135922330069, 0.2779922779922851}"
    },
    {
      "_class": "curvePoint",
      "cornerRadius": 0,
      "curveFrom": "{0.1262135922330069, 0.2779922779922851}",
      "curveMode": 1,
      "curveTo": "{0.1262135922330069, 0.2779922779922851}",
      "hasCurveFrom": false,
      "hasCurveTo": false,
      "point": "{0.1262135922330069, 0.2779922779922851}"
    },
    {
      "_class": "curvePoint",
      "cornerRadius": 0,
      "curveFrom": "{0.082524271844655175, 0.2779922779922851}",
      "curveMode": 1,
      "curveTo": "{0.082524271844655175, 0.2779922779922851}",
      "hasCurveFrom": false,
      "hasCurveTo": false,
      "point": "{0.082524271844655175, 0.2779922779922851}"
    },
    {
      "_class": "curvePoint",
      "cornerRadius": 0,
      "curveFrom": "{0.055459975591905152, 0.28355027828693152}",
      "curveMode": 4,
      "curveTo": "{0.082524271844655175, 0.2779922779922851}",
      "hasCurveFrom": true,
      "hasCurveTo": false,
      "point": "{0.082524271844655175, 0.2779922779922851}"
    },
    {
      "_class": "curvePoint",
      "cornerRadius": 0,
      "curveFrom": "{0, 0.2779922779922851}",
      "curveMode": 4,
      "curveTo": "{0.027064296252763818, 0.28355027828693152}",
      "hasCurveFrom": false,
      "hasCurveTo": true,
      "point": "{0, 0.2779922779922851}"
    },
    {
      "_class": "curvePoint",
      "cornerRadius": 0,
      "curveFrom": "{0, 0.2779922779922851}",
      "curveMode": 1,
      "curveTo": "{0, 0.2779922779922851}",
      "hasCurveFrom": false,
      "hasCurveTo": false,
      "point": "{0, 0.2779922779922851}"
    },
    {
      "_class": "curvePoint",
      "cornerRadius": 0,
      "curveFrom": "{0, 0.2779922779922851}",
      "curveMode": 1,
      "curveTo": "{0, 0.2779922779922851}",
      "hasCurveFrom": false,
      "hasCurveTo": false,
      "point": "{0, 0.2779922779922851}"
    },
    {
      "_class": "curvePoint",
      "cornerRadius": 0,
      "curveFrom": "{0.048543689320386205, 0.34362934362934511}",
      "curveMode": 1,
      "curveTo": "{0.048543689320386205, 0.34362934362934511}",
      "hasCurveFrom": false,
      "hasCurveTo": false,
      "point": "{0.048543689320386205, 0.34362934362934511}"
    },
    {
      "_class": "curvePoint",
      "cornerRadius": 0,
      "curveFrom": "{0.092233009708737934, 0.36679536679536889}",
      "curveMode": 1,
      "curveTo": "{0.092233009708737934, 0.36679536679536889}",
      "hasCurveFrom": false,
      "hasCurveTo": false,
      "point": "{0.092233009708737934, 0.36679536679536889}"
    },
    {
      "_class": "curvePoint",
      "cornerRadius": 0,
      "curveFrom": "{0.12135922330097242, 0.36679536679536889}",
      "curveMode": 1,
      "curveTo": "{0.12135922330097242, 0.36679536679536889}",
      "hasCurveFrom": false,
      "hasCurveTo": false,
      "point": "{0.12135922330097242, 0.36679536679536889}"
    },
    {
      "_class": "curvePoint",
      "cornerRadius": 0,
      "curveFrom": "{0.12135922330097242, 0.36679536679536889}",
      "curveMode": 1,
      "curveTo": "{0.12135922330097242, 0.36679536679536889}",
      "hasCurveFrom": false,
      "hasCurveTo": false,
      "point": "{0.12135922330097242, 0.36679536679536889}"
    },
    {
      "_class": "curvePoint",
      "cornerRadius": 0,
      "curveFrom": "{0.12135922330097242, 0.36679536679536889}",
      "curveMode": 1,
      "curveTo": "{0.12135922330097242, 0.36679536679536889}",
      "hasCurveFrom": false,
      "hasCurveTo": false,
      "point": "{0.12135922330097242, 0.36679536679536889}"
    },
    {
      "_class": "curvePoint",
      "cornerRadius": 0,
      "curveFrom": "{0.12135922330097242, 0.36679536679536889}",
      "curveMode": 1,
      "curveTo": "{0.12135922330097242, 0.36679536679536889}",
      "hasCurveFrom": false,
      "hasCurveTo": false,
      "point": "{0.12135922330097242, 0.36679536679536889}"
    },
    {
      "_class": "curvePoint",
      "cornerRadius": 0,
      "curveFrom": "{0.12135922330097242, 0.39768339768340422}",
      "curveMode": 1,
      "curveTo": "{0.12135922330097242, 0.39768339768340422}",
      "hasCurveFrom": false,
      "hasCurveTo": false,
      "point": "{0.12135922330097242, 0.39768339768340422}"
    },
    {
      "_class": "curvePoint",
      "cornerRadius": 0,
      "curveFrom": "{0.12135922330097242, 0.44015444015445143}",
      "curveMode": 1,
      "curveTo": "{0.12135922330097242, 0.44015444015445143}",
      "hasCurveFrom": false,
      "hasCurveTo": false,
      "point": "{0.12135922330097242, 0.44015444015445143}"
    },
    {
      "_class": "curvePoint",
      "cornerRadius": 0,
      "curveFrom": "{0.12135922330097242, 0.44015444015445143}",
      "curveMode": 1,
      "curveTo": "{0.12135922330097242, 0.44015444015445143}",
      "hasCurveFrom": false,
      "hasCurveTo": false,
      "point": "{0.12135922330097242, 0.44015444015445143}"
    },
    {
      "_class": "curvePoint",
      "cornerRadius": 0,
      "curveFrom": "{0.12135922330097242, 0.44015444015445143}",
      "curveMode": 1,
      "curveTo": "{0.12135922330097242, 0.44015444015445143}",
      "hasCurveFrom": false,
      "hasCurveTo": false,
      "point": "{0.12135922330097242, 0.44015444015445143}"
    },
    {
      "_class": "curvePoint",
      "cornerRadius": 0,
      "curveFrom": "{0.12135922330097242, 0.46718146718147546}",
      "curveMode": 1,
      "curveTo": "{0.12135922330097242, 0.46718146718147546}",
      "hasCurveFrom": false,
      "hasCurveTo": false,
      "point": "{0.12135922330097242, 0.46718146718147546}"
    },
    {
      "_class": "curvePoint",
      "cornerRadius": 0,
      "curveFrom": "{0.16019417475728967, 0.46718146718147546}",
      "curveMode": 1,
      "curveTo": "{0.16019417475728967, 0.46718146718147546}",
      "hasCurveFrom": false,
      "hasCurveTo": false,
      "point": "{0.16019417475728967, 0.46718146718147546}"
    },
    {
      "_class": "curvePoint",
      "cornerRadius": 0,
      "curveFrom": "{0.18446601941748966, 0.46718146718147546}",
      "curveMode": 1,
      "curveTo": "{0.18446601941748966, 0.46718146718147546}",
      "hasCurveFrom": false,
      "hasCurveTo": false,
      "point": "{0.18446601941748966, 0.46718146718147546}"
    },
    {
      "_class": "curvePoint",
      "cornerRadius": 0,
      "curveFrom": "{0.21844660194175863, 0.46718146718147546}",
      "curveMode": 1,
      "curveTo": "{0.21844660194175863, 0.46718146718147546}",
      "hasCurveFrom": false,
      "hasCurveTo": false,
      "point": "{0.21844660194175863, 0.46718146718147546}"
    },
    {
      "_class": "curvePoint",
      "cornerRadius": 0,
      "curveFrom": "{0.21844660194175863, 0.46718146718147546}",
      "curveMode": 1,
      "curveTo": "{0.21844660194175863, 0.46718146718147546}",
      "hasCurveFrom": false,
      "hasCurveTo": false,
      "point": "{0.21844660194175863, 0.46718146718147546}"
    },
    {
      "_class": "curvePoint",
      "cornerRadius": 0,
      "curveFrom": "{0.27184466019419312, 0.48648648648649895}",
      "curveMode": 1,
      "curveTo": "{0.27184466019419312, 0.48648648648649895}",
      "hasCurveFrom": false,
      "hasCurveTo": false,
      "point": "{0.27184466019419312, 0.48648648648649895}"
    },
    {
      "_class": "curvePoint",
      "cornerRadius": 0,
      "curveFrom": "{0.27184466019419312, 0.48648648648649895}",
      "curveMode": 1,
      "curveTo": "{0.27184466019419312, 0.48648648648649895}",
      "hasCurveFrom": false,
      "hasCurveTo": false,
      "point": "{0.27184466019419312, 0.48648648648649895}"
    },
    {
      "_class": "curvePoint",
      "cornerRadius": 0,
      "curveFrom": "{0.27184466019419312, 0.50579150579152243}",
      "curveMode": 1,
      "curveTo": "{0.27184466019419312, 0.50579150579152243}",
      "hasCurveFrom": false,
      "hasCurveTo": false,
      "point": "{0.27184466019419312, 0.50579150579152243}"
    },
    {
      "_class": "curvePoint",
      "cornerRadius": 0,
      "curveFrom": "{0.25976242087447532, 0.52390061220192219}",
      "curveMode": 4,
      "curveTo": "{0.27184466019419312, 0.50579150579152243}",
      "hasCurveFrom": true,
      "hasCurveTo": false,
      "point": "{0.27184466019419312, 0.50579150579152243}"
    },
    {
      "_class": "curvePoint",
      "cornerRadius": 0,
      "curveFrom": "{0.27184466019419312, 0.56370656370658179}",
      "curveMode": 4,
      "curveTo": "{0.25976242087447532, 0.54559745729619291}",
      "hasCurveFrom": false,
      "hasCurveTo": true,
      "point": "{0.27184466019419312, 0.56370656370658179}"
    },
    {
      "_class": "curvePoint",
      "cornerRadius": 0,
      "curveFrom": "{0.27184466019419312, 0.61389961389962966}",
      "curveMode": 1,
      "curveTo": "{0.27184466019419312, 0.61389961389962966}",
      "hasCurveFrom": false,
      "hasCurveTo": false,
      "point": "{0.27184466019419312, 0.61389961389962966}"
    },
    {
      "_class": "curvePoint",
      "cornerRadius": 0,
      "curveFrom": "{0.27184466019419312, 0.63706563706565333}",
      "curveMode": 1,
      "curveTo": "{0.27184466019419312, 0.63706563706565333}",
      "hasCurveFrom": false,
      "hasCurveTo": false,
      "point": "{0.27184466019419312, 0.63706563706565333}"
    },
    {
      "_class": "curvePoint",
      "cornerRadius": 0,
      "curveFrom": "{0.27184466019419312, 0.63706563706565333}",
      "curveMode": 1,
      "curveTo": "{0.27184466019419312, 0.63706563706565333}",
      "hasCurveFrom": false,
      "hasCurveTo": false,
      "point": "{0.27184466019419312, 0.63706563706565333}"
    },
    {
      "_class": "curvePoint",
      "cornerRadius": 0,
      "curveFrom": "{0.27184466019419312, 0.63706563706565333}",
      "curveMode": 1,
      "curveTo": "{0.27184466019419312, 0.63706563706565333}",
      "hasCurveFrom": false,
      "hasCurveTo": false,
      "point": "{0.27184466019419312, 0.63706563706565333}"
    },
    {
      "_class": "curvePoint",
      "cornerRadius": 0,
      "curveFrom": "{0.27184466019419312, 0.63706563706565333}",
      "curveMode": 1,
      "curveTo": "{0.27184466019419312, 0.63706563706565333}",
      "hasCurveFrom": false,
      "hasCurveTo": false,
      "point": "{0.27184466019419312, 0.63706563706565333}"
    },
    {
      "_class": "curvePoint",
      "cornerRadius": 0,
      "curveFrom": "{0.27184466019419312, 0.66409266409267742}",
      "curveMode": 1,
      "curveTo": "{0.27184466019419312, 0.66409266409267742}",
      "hasCurveFrom": false,
      "hasCurveTo": false,
      "point": "{0.27184466019419312, 0.66409266409267742}"
    },
    {
      "_class": "curvePoint",
      "cornerRadius": 0,
      "curveFrom": "{0.27184466019419312, 0.68725868725870121}",
      "curveMode": 1,
      "curveTo": "{0.27184466019419312, 0.68725868725870121}",
      "hasCurveFrom": false,
      "hasCurveTo": false,
      "point": "{0.27184466019419312, 0.68725868725870121}"
    },
    {
      "_class": "curvePoint",
      "cornerRadius": 0,
      "curveFrom": "{0.23786407766992415, 0.70656370656372469}",
      "curveMode": 4,
      "curveTo": "{0.27184466019419312, 0.68725868725870121}",
      "hasCurveFrom": true,
      "hasCurveTo": false,
      "point": "{0.27184466019419312, 0.68725868725870121}"
    },
    {
      "_class": "curvePoint",
      "cornerRadius": 0,
      "curveFrom": "{0.35436893203884828, 0.77606177606178495}",
      "curveMode": 4,
      "curveTo": "{0.30097087378642762, 0.76447876447877305}",
      "hasCurveFrom": false,
      "hasCurveTo": true,
      "point": "{0.35436893203884828, 0.77606177606178495}"
    },
    {
      "_class": "curvePoint",
      "cornerRadius": 0,
      "curveFrom": "{0.35436893203884828, 0.77606177606178495}",
      "curveMode": 1,
      "curveTo": "{0.35436893203884828, 0.77606177606178495}",
      "hasCurveFrom": false,
      "hasCurveTo": false,
      "point": "{0.35436893203884828, 0.77606177606178495}"
    },
    {
      "_class": "curvePoint",
      "cornerRadius": 0,
      "curveFrom": "{0.35436893203884828, 0.77606177606178495}",
      "curveMode": 1,
      "curveTo": "{0.35436893203884828, 0.77606177606178495}",
      "hasCurveFrom": false,
      "hasCurveTo": false,
      "point": "{0.35436893203884828, 0.77606177606178495}"
    },
    {
      "_class": "curvePoint",
      "cornerRadius": 0,
      "curveFrom": "{0.38411136438562865, 0.82054755564652926}",
      "curveMode": 4,
      "curveTo": "{0.35436893203884828, 0.79922779922780873}",
      "hasCurveFrom": true,
      "hasCurveTo": false,
      "point": "{0.35436893203884828, 0.79922779922780873}"
    },
    {
      "_class": "curvePoint",
      "cornerRadius": 0,
      "curveFrom": "{0.46116504854370344, 0.83783783783785559}",
      "curveMode": 4,
      "curveTo": "{0.42141288062048993, 0.83403318629654899}",
      "hasCurveFrom": false,
      "hasCurveTo": true,
      "point": "{0.46116504854370344, 0.83783783783785559}"
    },
    {
      "_class": "curvePoint",
      "cornerRadius": 0,
      "curveFrom": "{0.46116504854370344, 0.86486486486487968}",
      "curveMode": 1,
      "curveTo": "{0.46116504854370344, 0.86486486486487968}",
      "hasCurveFrom": false,
      "hasCurveTo": false,
      "point": "{0.46116504854370344, 0.86486486486487968}"
    },
    {
      "_class": "curvePoint",
      "cornerRadius": 0,
      "curveFrom": "{0.52427184466020693, 0.86486486486487968}",
      "curveMode": 1,
      "curveTo": "{0.52427184466020693, 0.86486486486487968}",
      "hasCurveFrom": false,
      "hasCurveTo": false,
      "point": "{0.52427184466020693, 0.86486486486487968}"
    },
    {
      "_class": "curvePoint",
      "cornerRadius": 0,
      "curveFrom": "{0.52427184466020693, 0.86486486486487968}",
      "curveMode": 1,
      "curveTo": "{0.52427184466020693, 0.86486486486487968}",
      "hasCurveFrom": false,
      "hasCurveTo": false,
      "point": "{0.52427184466020693, 0.86486486486487968}"
    },
    {
      "_class": "curvePoint",
      "cornerRadius": 0,
      "curveFrom": "{0.55339805825244137, 0.86486486486487968}",
      "curveMode": 1,
      "curveTo": "{0.55339805825244137, 0.86486486486487968}",
      "hasCurveFrom": false,
      "hasCurveTo": false,
      "point": "{0.55339805825244137, 0.86486486486487968}"
    },
    {
      "_class": "curvePoint",
      "cornerRadius": 0,
      "curveFrom": "{0.60679611650487586, 0.84169884169885589}",
      "curveMode": 1,
      "curveTo": "{0.60679611650487586, 0.84169884169885589}",
      "hasCurveFrom": false,
      "hasCurveTo": false,
      "point": "{0.60679611650487586, 0.84169884169885589}"
    },
    {
      "_class": "curvePoint",
      "cornerRadius": 0,
      "curveFrom": "{0.60679611650487586, 0.84169884169885589}",
      "curveMode": 1,
      "curveTo": "{0.60679611650487586, 0.84169884169885589}",
      "hasCurveFrom": false,
      "hasCurveTo": false,
      "point": "{0.60679611650487586, 0.84169884169885589}"
    },
    {
      "_class": "curvePoint",
      "cornerRadius": 0,
      "curveFrom": "{0.60679611650487586, 0.84169884169885589}",
      "curveMode": 1,
      "curveTo": "{0.60679611650487586, 0.84169884169885589}",
      "hasCurveFrom": false,
      "hasCurveTo": false,
      "point": "{0.60679611650487586, 0.84169884169885589}"
    },
    {
      "_class": "curvePoint",
      "cornerRadius": 0,
      "curveFrom": "{0.66019417475731035, 0.84169884169885589}",
      "curveMode": 1,
      "curveTo": "{0.66019417475731035, 0.84169884169885589}",
      "hasCurveFrom": false,
      "hasCurveTo": false,
      "point": "{0.66019417475731035, 0.84169884169885589}"
    }
  ],
  "resizingConstraint": 63,
  "resizingType": 0,
  "rotation": 0,
  "shouldBreakMaskChain": false,
  "style": {
    "_class": "style",
    "blur": {
      "_class": "blur",
      "center": "{0.5, 0.5}",
      "isEnabled": false,
      "motionAngle": 0,
      "radius": 10,
      "saturation": 1,
      "type": 0
    },
    "borderOptions": {
      "_class": "borderOptions",
      "dashPattern": [
      ],
      "isEnabled": true,
      "lineCapStyle": 0,
      "lineJoinStyle": 0
    },
    "borders": [
    ],
    "colorControls": {
      "_class": "colorControls",
      "brightness": 0,
      "contrast": 1,
      "hue": 0,
      "isEnabled": false,
      "saturation": 1
    },
    "contextSettings": {
      "_class": "graphicsContextSettings",
      "blendMode": 0,
      "opacity": 1
    },
    "do_objectID": "A454C14C-421D-490E-A1C1-2A7D62E6BD1C",
    "endMarkerType": 0,
    "fills": [
    ],
    "innerShadows": [
    ],
    "miterLimit": 10,
    "shadows": [
    ],
    "startMarkerType": 0,
    "windingRule": 1
  }
}