{
  "_class": "shapePath",
  "booleanOperation": -1,
  "clippingMaskMode": 0,
  "do_objectID": "FB209AB0-2A5B-4911-A687-81A65B95FCB8",
  "edited": true,
  "frame": {
    "_class": "rect",
    "constrainProportions": false,
    "height": 1,
    "width": 1.47503888351315,
    "x": 112.43,
    "y": 246.2461411281997
  },
  "hasClippingMask": false,
  "isClosed": true,
  "isFixedToViewport": false,
  "isFlippedHorizontal": false,
  "isFlippedVertical": false,
  "isLocked": false,
  "isVisible": true,
  "layerListExpandedType": 0,
  "name": "Path",
  "nameIsFixed": false,
  "pointRadiusBehaviour": 1,
  "points": [
    {
      "_class": "curvePoint",
      "cornerRadius": 0,
      "curveFrom": "{0.75400631606845547, 0.12623396868883674}",
      "curveMode": 4,
      "curveTo": "{0.83387632268410805, 0.31385887180027794}",
      "hasCurveFrom": true,
      "hasCurveTo": true,
      "point": "{0.81353787578937331, 0.25385887180027567}"
    },
    {
      "_class": "curvePoint",
      "cornerRadius": 0,
      "curveFrom": "{0.55591754845607844, 0.023858871800257475}",
      "curveMode": 4,
      "curveTo": "{0.66018197622885322, 0.042468846633084922}",
      "hasCurveFrom": false,
      "hasCurveTo": true,
      "point": "{0.55591754845607844, 0.023858871800257475}"
    },
    {
      "_class": "curvePoint",
      "cornerRadius": 0,
      "curveFrom": "{0.55591754845607844, 0.023858871800257475}",
      "curveMode": 1,
      "curveTo": "{0.55591754845607844, 0.023858871800257475}",
      "hasCurveFrom": false,
      "hasCurveTo": false,
      "point": "{0.55591754845607844, 0.023858871800257475}"
    },
    {
      "_class": "curvePoint",
      "cornerRadius": 0,
      "curveFrom": "{0.48134324317537774, 0.023858871800257475}",
      "curveMode": 1,
      "curveTo": "{0.48134324317537774, 0.023858871800257475}",
      "hasCurveFrom": false,
      "hasCurveTo": false,
      "point": "{0.48134324317537774, 0.023858871800257475}"
    },
    {
      "_class": "curvePoint",
      "cornerRadius": 0,
      "curveFrom": "{0.28190572821208326, -0.0047499726277919763}",
      "curveMode": 4,
      "curveTo": "{0.38643049099996146, 0.023858871800257475}",
      "hasCurveFrom": true,
      "hasCurveTo": false,
      "point": "{0.38643049099996146, 0.023858871800257475}"
    },
    {
      "_class": "curvePoint",
      "cornerRadius": 0,
      "curveFrom": "{0.088133269877177761, 0.12385887180028021}",
      "curveMode": 4,
      "curveTo": "{0.17400733023754386, 0.031421466572453483}",
      "hasCurveFrom": false,
      "hasCurveTo": true,
      "point": "{0.088133269877177761, 0.12385887180028021}"
    },
    {
      "_class": "curvePoint",
      "cornerRadius": 0,
      "curveFrom": "{0.047456376087708141, 0.12385887180028021}",
      "curveMode": 1,
      "curveTo": "{0.047456376087708141, 0.12385887180028021}",
      "hasCurveFrom": false,
      "hasCurveTo": false,
      "point": "{0.047456376087708141, 0.12385887180028021}"
    },
    {
      "_class": "curvePoint",
      "cornerRadius": 0,
      "curveFrom": "{0, 0.22385887180030295}",
      "curveMode": 1,
      "curveTo": "{0, 0.22385887180030295}",
      "hasCurveFrom": false,
      "hasCurveTo": false,
      "point": "{0, 0.22385887180030295}"
    },
    {
      "_class": "curvePoint",
      "cornerRadius": 0,
      "curveFrom": "{0, 0.41385887180030068}",
      "curveMode": 1,
      "curveTo": "{0, 0.41385887180030068}",
      "hasCurveFrom": false,
      "hasCurveTo": false,
      "point": "{0, 0.41385887180030068}"
    },
    {
      "_class": "curvePoint",
      "cornerRadius": 0,
      "curveFrom": "{0, 0.49385887180028476}",
      "curveMode": 1,
      "curveTo": "{0, 0.49385887180028476}",
      "hasCurveFrom": false,
      "hasCurveTo": false,
      "point": "{0, 0.49385887180028476}"
    },
    {
      "_class": "curvePoint",
      "cornerRadius": 0,
      "curveFrom": "{0, 0.58385887180025975}",
      "curveMode": 1,
      "curveTo": "{0, 0.58385887180025975}",
      "hasCurveFrom": false,
      "hasCurveTo": false,
      "point": "{0, 0.58385887180025975}"
    },
    {
      "_class": "curvePoint",
      "cornerRadius": 0,
      "curveFrom": "{0.094912752175416282, 0.7038588718002643}",
      "curveMode": 4,
      "curveTo": "{0, 0.58385887180025975}",
      "hasCurveFrom": true,
      "hasCurveTo": false,
      "point": "{0, 0.58385887180025975}"
    },
    {
      "_class": "curvePoint",
      "cornerRadius": 0,
      "curveFrom": "{0.1181427167910549, 0.86105243128230313}",
      "curveMode": 4,
      "curveTo": "{0.094912752175416282, 0.7038588718002643}",
      "hasCurveFrom": true,
      "hasCurveTo": true,
      "point": "{0.10847171677191259, 0.77385887180025748}"
    },
    {
      "_class": "curvePoint",
      "cornerRadius": 0,
      "curveFrom": "{0.21016395124558665, 0.97385887180024611}",
      "curveMode": 4,
      "curveTo": "{0.15612362072009164, 0.93575017811741645}",
      "hasCurveFrom": false,
      "hasCurveTo": true,
      "point": "{0.21016395124558665, 0.97385887180024611}"
    },
    {
      "_class": "curvePoint",
      "cornerRadius": 0,
      "curveFrom": "{0.33219463261399551, 0.97385887180024611}",
      "curveMode": 4,
      "curveTo": "{0.24406136273681775, 0.97385887180024611}",
      "hasCurveFrom": true,
      "hasCurveTo": false,
      "point": "{0.24406136273681775, 0.97385887180024611}"
    },
    {
      "_class": "curvePoint",
      "cornerRadius": 0,
      "curveFrom": "{0.54913806615782068, 0.88385887180027112}",
      "curveMode": 4,
      "curveTo": "{0.36609204410522661, 1.0338588718002484}",
      "hasCurveFrom": false,
      "hasCurveTo": true,
      "point": "{0.54913806615782068, 0.88385887180027112}"
    },
    {
      "_class": "curvePoint",
      "cornerRadius": 0,
      "curveFrom": "{0.86099425187708145, 0.88385887180027112}",
      "curveMode": 4,
      "curveTo": "{0.67116874752622957, 0.88385887180027112}",
      "hasCurveFrom": true,
      "hasCurveTo": false,
      "point": "{0.67116874752622957, 0.88385887180027112}"
    },
    {
      "_class": "curvePoint",
      "cornerRadius": 0,
      "curveFrom": "{1.0169223447367022, 0.48385887180029385}",
      "curveMode": 2,
      "curveTo": "{0.97624545094723247, 0.88385887180027112}",
      "hasCurveFrom": true,
      "hasCurveTo": true,
      "point": "{0.99658389784196733, 0.68385887180028249}"
    },
    {
      "_class": "curvePoint",
      "cornerRadius": 0,
      "curveFrom": "{0.82031735808763107, 0.29385887180023929}",
      "curveMode": 2,
      "curveTo": "{0.94234803945600143, 0.3538588718002984}",
      "hasCurveFrom": true,
      "hasCurveTo": true,
      "point": "{0.88133269877181619, 0.32385887180026884}"
    }
  ],
  "resizingConstraint": 63,
  "resizingType": 0,
  "rotation": 0,
  "shouldBreakMaskChain": false,
  "style": {
    "_class": "style",
    "blur": {
      "_class": "blur",
      "center": "{0.5, 0.5}",
      "isEnabled": false,
      "motionAngle": 0,
      "radius": 10,
      "saturation": 1,
      "type": 0
    },
    "borderOptions": {
      "_class": "borderOptions",
      "dashPattern": [
      ],
      "isEnabled": true,
      "lineCapStyle": 0,
      "lineJoinStyle": 0
    },
    "borders": [
    ],
    "colorControls": {
      "_class": "colorControls",
      "brightness": 0,
      "contrast": 1,
      "hue": 0,
      "isEnabled": false,
      "saturation": 1
    },
    "contextSettings": {
      "_class": "graphicsContextSettings",
      "blendMode": 0,
      "opacity": 1
    },
    "do_objectID": "E3FAC71F-78B3-42E9-BC10-3F5EEF065126",
    "endMarkerType": 0,
    "fills": [
      {
        "_class": "fill",
        "color": {
          "_class": "color",
          "alpha": 1,
          "blue": 0.7215686274509804,
          "green": 0.4392156862745098,
          "red": 0.06666666666666667
        },
        "contextSettings": {
          "_class": "graphicsContextSettings",
          "blendMode": 0,
          "opacity": 1
        },
        "fillType": 0,
        "gradient": {
          "_class": "gradient",
          "elipseLength": 0,
          "from": "{0.5, 0}",
          "gradientType": 0,
          "stops": [
            {
              "_class": "gradientStop",
              "color": {
                "_class": "color",
                "alpha": 1,
                "blue": 1,
                "green": 1,
                "red": 1
              },
              "position": 0
            },
            {
              "_class": "gradientStop",
              "color": {
                "_class": "color",
                "alpha": 1,
                "blue": 0,
                "green": 0,
                "red": 0
              },
              "position": 1
            }
          ],
          "to": "{0.5, 1}"
        },
        "isEnabled": true,
        "noiseIndex": 0,
        "noiseIntensity": 0,
        "patternFillType": 1,
        "patternTileScale": 1
      }
    ],
    "innerShadows": [
    ],
    "miterLimit": 10,
    "shadows": [
    ],
    "startMarkerType": 0,
    "windingRule": 0
  }
}