{
  "_class": "group",
  "booleanOperation": -1,
  "clippingMaskMode": 0,
  "do_objectID": "8BA70E4B-9F95-4518-9A9A-F43E5608CFF8",
  "frame": {
    "_class": "rect",
    "constrainProportions": false,
    "height": 32,
    "width": 448,
    "x": 0,
    "y": 0
  },
  "groupLayout": {
    "_class": "MSImmutableFreeformGroupLayout"
  },
  "hasClickThrough": false,
  "hasClippingMask": false,
  "isFixedToViewport": false,
  "isFlippedHorizontal": false,
  "isFlippedVertical": false,
  "isLocked": false,
  "isVisible": true,
  "layerListExpandedType": 0,
  "layers": [
    {
      "class": "group",
      "id": "F0E87F99-856D-4B2D-B258-8FD8708C6D0C"
    },
    {
      "class": "group",
      "id": "6FDBF3F8-14B5-4F15-B1D7-D2B84650AABD"
    },
    {
      "class": "group",
      "id": "0ECFBC61-5A28-4FE4-97D7-FFD06D366CB3"
    },
    {
      "class": "group",
      "id": "93811021-23A2-4C23-92A9-DF9EB0F114FD"
    },
    {
      "class": "group",
      "id": "8ACA51E7-D7D1-4261-8304-DFE484BCE90C"
    },
    {
      "class": "group",
      "id": "77925C04-6E7D-419E-93F2-0CA5FCF59A06"
    },
    {
      "class": "group",
      "id": "F10C2B1E-188A-407C-ACE5-43FB52773C90"
    },
    {
      "class": "group",
      "id": "A2B94CA5-F392-41B4-8AB8-59E275501A53"
    },
    {
      "class": "group",
      "id": "268C28A1-4A09-4B18-9523-17F3E08DFB5C"
    },
    {
      "class": "group",
      "id": "3F3AC7FE-515C-4CD0-82C9-E068266CD6AD"
    },
    {
      "class": "group",
      "id": "C2CE29B6-F885-48EB-81AF-12CA60993FF9"
    }
  ],
  "name": "Group 15",
  "nameIsFixed": false,
  "resizingConstraint": 63,
  "resizingType": 0,
  "rotation": 0,
  "shouldBreakMaskChain": false,
  "style": {
    "_class": "style",
    "blur": {
      "_class": "blur",
      "center": "{0.5, 0.5}",
      "isEnabled": false,
      "motionAngle": 0,
      "radius": 10,
      "saturation": 1,
      "type": 0
    },
    "borderOptions": {
      "_class": "borderOptions",
      "dashPattern": [
      ],
      "isEnabled": true,
      "lineCapStyle": 0,
      "lineJoinStyle": 0
    },
    "borders": [
    ],
    "colorControls": {
      "_class": "colorControls",
      "brightness": 0,
      "contrast": 1,
      "hue": 0,
      "isEnabled": false,
      "saturation": 1
    },
    "contextSettings": {
      "_class": "graphicsContextSettings",
      "blendMode": 0,
      "opacity": 1
    },
    "do_objectID": "84938B26-8A4E-487B-B6F5-72A27B924A3C",
    "endMarkerType": 0,
    "fills": [
    ],
    "innerShadows": [
    ],
    "miterLimit": 10,
    "shadows": [
    ],
    "startMarkerType": 0,
    "windingRule": 1
  }
}